wmdan05/__init__.py
wmdan05/danish05_module.py
wmdan05-0.1.0.dist-info/licenses/LICENSE
wmdan05-0.1.0.dist-info/WHEEL
wmdan05-0.1.0.dist-info/METADATA
wmdan05-0.1.0.dist-info/RECORD
