Metadata-Version: 2.4
Name: wmdan05
Version: 0.1.0
Summary: Danish05 Watermark Package
Author: Danish05
License-Expression: MIT
License-File: LICENSE
